pykubeyaml.py
pykubeyaml-0.0.2.dist-info/METADATA
pykubeyaml-0.0.2.dist-info/RECORD
pykubeyaml-0.0.2.dist-info/WHEEL
pykubeyaml-0.0.2.dist-info/entry_points.txt
pykubeyaml-0.0.2.dist-info/top_level.txt
